vkwave/__init__.py
vkwave/api/__init__.py
vkwave/api/methods/__init__.py
vkwave/api/methods/_abc.py
vkwave/api/methods/_category.py
vkwave/api/methods/_error.py
vkwave/api/methods/_utils.py
vkwave/api/methods/account.py
vkwave/api/methods/ads.py
vkwave/api/methods/adsweb.py
vkwave/api/methods/app_widgets.py
vkwave/api/methods/apps.py
vkwave/api/methods/audio.py
vkwave/api/methods/auth.py
vkwave/api/methods/board.py
vkwave/api/methods/database.py
vkwave/api/methods/docs.py
vkwave/api/methods/donut.py
vkwave/api/methods/downloaded_games.py
vkwave/api/methods/execute.py
vkwave/api/methods/fave.py
vkwave/api/methods/friends.py
vkwave/api/methods/gifts.py
vkwave/api/methods/groups.py
vkwave/api/methods/leads.py
vkwave/api/methods/likes.py
vkwave/api/methods/market.py
vkwave/api/methods/messages.py
vkwave/api/methods/money.py
vkwave/api/methods/newsfeed.py
vkwave/api/methods/notes.py
vkwave/api/methods/notifications.py
vkwave/api/methods/orders.py
vkwave/api/methods/pages.py
vkwave/api/methods/photos.py
vkwave/api/methods/podcasts.py
vkwave/api/methods/polls.py
vkwave/api/methods/pretty_cards.py
vkwave/api/methods/search.py
vkwave/api/methods/secure.py
vkwave/api/methods/stats.py
vkwave/api/methods/status.py
vkwave/api/methods/storage.py
vkwave/api/methods/stories.py
vkwave/api/methods/streaming.py
vkwave/api/methods/users.py
vkwave/api/methods/utils.py
vkwave/api/methods/video.py
vkwave/api/methods/wall.py
vkwave/api/methods/widgets.py
vkwave/api/token/__init__.py
vkwave/api/token/strategy.py
vkwave/api/token/token.py
vkwave/api/utils/get_all.py
vkwave/bots/__init__.py
vkwave/bots/addons/__init__.py
vkwave/bots/addons/cache/__init__.py
vkwave/bots/addons/cache/cached_filter.py
vkwave/bots/addons/class_based_handlers.py
vkwave/bots/addons/easy/__init__.py
vkwave/bots/addons/easy/base_easy_bot.py
vkwave/bots/addons/easy/clones_bot.py
vkwave/bots/addons/easy/easy_bot.py
vkwave/bots/addons/easy/easy_handlers.py
vkwave/bots/addons/easy/easy_userbot.py
vkwave-0.2.17.dist-info/LICENSE
vkwave-0.2.17.dist-info/WHEEL
vkwave-0.2.17.dist-info/METADATA
vkwave-0.2.17.dist-info/RECORD
