Metadata-Version: 2.1
Name: vkwave
Version: 0.2.17
Summary: Framework for building high-performance & easy to scale projects interacting with VK's API.
Home-page: https://github.com/fscdev/vkwave
License: MIT
Keywords: vk,vkontakte,api,framework,wrapper,asyncio,bots
Author: prostomarkeloff
Requires-Python: >=3.7,<4.0
Classifier: Environment :: Console
Classifier: Framework :: AsyncIO
Classifier: Intended Audience :: Developers
Classifier: Intended Audience :: System Administrators
Classifier: License :: OSI Approved :: MIT License
Classifier: Programming Language :: Python :: 3
Classifier: Programming Language :: Python :: 3.10
Classifier: Programming Language :: Python :: 3.7
Classifier: Programming Language :: Python :: 3.8
Classifier: Programming Language :: Python :: 3.9
Classifier: Topic :: Software Development :: Libraries :: Application Frameworks
Classifier: Typing :: Typed
Provides-Extra: all
Provides-Extra: storage-redis
Requires-Dist: aiohttp (>=3.6,<4.0)
Requires-Dist: aioredis (>=1.3,<2.0); extra == "storage-redis" or extra == "all"
Requires-Dist: pydantic (>=1.7,<2.0)
Requires-Dist: typing_extensions (>=3.7.4,<4.0.0)
Project-URL: Bug Tracker, https://github.com/fscdev/vkwave/issues
Project-URL: Repository, https://github.com/fscdev/vkwave
